vargur_api_sdk/__init__.py
vargur_api_sdk/auth.py
vargur_api_sdk/cache.py
vargur_api_sdk/config.py
vargur_api_sdk/core.py
vargur_api_sdk/database.py
vargur_api_sdk/events.py
vargur_api_sdk-0.0.1.dist-info/LICENSE
vargur_api_sdk-0.0.1.dist-info/METADATA
vargur_api_sdk-0.0.1.dist-info/WHEEL
vargur_api_sdk-0.0.1.dist-info/RECORD
