Metadata-Version: 2.1
Name: vargur-api-sdk
Version: 0.0.1
Summary: EVE ONLINE - Vargur API SDK
Home-page: https://github.com/meloncafe/vargur-api-sdk
License: MIT
Keywords: eve online,sdk,api
Author: MelonCafe
Author-email: contact@siege0green.com
Requires-Python: >=3.11,<4.0
Classifier: Development Status :: 3 - Alpha
Classifier: Intended Audience :: Developers
Classifier: License :: OSI Approved :: MIT License
Classifier: Operating System :: OS Independent
Classifier: Programming Language :: Python :: 3
Classifier: Programming Language :: Python :: 3.11
Classifier: Programming Language :: Python :: 3.12
Requires-Dist: fastapi (>=0.111.0,<0.112.0)
Requires-Dist: mkdocs (>=1.6.0,<2.0.0)
Requires-Dist: mkdocs-git-revision-date-localized-plugin (>=1.2.6,<2.0.0)
Requires-Dist: mkdocs-i18n (>=0.4.6,<0.5.0)
Requires-Dist: mkdocs-material (>=9.5.28,<10.0.0)
Requires-Dist: mkdocs-minify-plugin (>=0.8.0,<0.9.0)
Requires-Dist: sqlalchemy (>=2.0.31,<3.0.0)
Project-URL: Documentation, https://vargur-api-sdk.siege-green.com
Project-URL: Repository, https://github.com/meloncafe/vargur-api-sdk
